pydroid_ipcam/__init__.py
pydroid_ipcam/exceptions.py
pydroid_ipcam/py.typed
pydroid_ipcam_audio-2.1.0.dist-info/LICENSE
pydroid_ipcam_audio-2.1.0.dist-info/METADATA
pydroid_ipcam_audio-2.1.0.dist-info/WHEEL
pydroid_ipcam_audio-2.1.0.dist-info/top_level.txt
pydroid_ipcam_audio-2.1.0.dist-info/zip-safe
pydroid_ipcam_audio-2.1.0.dist-info/RECORD
